apexauthlib/__init__.py
apexauthlib/entities/__init__.py
apexauthlib/entities/auth.py
apexauthlib/fastapi/__init__.py
apexauthlib/fastapi/auth.py
apexauthlib/integration/__init__.py
apexauthlib/integration/api.py
apexauthlib/integration/formatter.py
apexauthlib-0.1.10.dist-info/METADATA
apexauthlib-0.1.10.dist-info/WHEEL
apexauthlib-0.1.10.dist-info/licenses/LICENSE
apexauthlib-0.1.10.dist-info/RECORD
