Metadata-Version: 2.4
Name: apexauthlib
Version: 0.1.10
Summary: Apex authorization library for services
License-File: LICENSE
Author: Apex Dev
Author-email: dev@apex.ge
Requires-Python: >=3.11
Classifier: Programming Language :: Python :: 3
Classifier: Programming Language :: Python :: 3.12
Classifier: Programming Language :: Python :: 3.13
Classifier: Programming Language :: Python :: 3.14
Requires-Dist: apexdevkit
Requires-Dist: fastapi (==0.120.*)
Requires-Dist: httpx
Requires-Dist: uvicorn
